logseq_doctor-0.3.0.dist-info/METADATA
logseq_doctor-0.3.0.dist-info/WHEEL
logseq_doctor-0.3.0.dist-info/entry_points.txt
logseq_doctor-0.3.0.dist-info/license_files/LICENSE
logseq_doctor-0.3.0.dist-info/license_files/AUTHORS.rst
logseq_doctor/constants.py
logseq_doctor/__main__.py
logseq_doctor/api.py
logseq_doctor/cli.py
logseq_doctor/__init__.py
logseq_doctor/rust_ext.cpython-39-aarch64-linux-gnu.so
logseq_doctor-0.3.0.dist-info/RECORD
