Metadata-Version: 2.1
Name: logseq-doctor
Version: 0.3.0
Classifier: Development Status :: 3 - Alpha
Classifier: Intended Audience :: Developers
Classifier: Intended Audience :: End Users/Desktop
Classifier: Operating System :: MacOS
Classifier: Operating System :: Unix
Classifier: Programming Language :: Python :: 3 :: Only
Classifier: Programming Language :: Python :: Implementation :: CPython
Classifier: Programming Language :: Python :: Implementation :: PyPy
Classifier: Programming Language :: Rust
Classifier: Topic :: Documentation
Classifier: Topic :: Office/Business
Classifier: Topic :: Scientific/Engineering
Classifier: Topic :: Text Processing :: Markup :: Markdown
Requires-Dist: maya
Requires-Dist: mistletoe
Requires-Dist: requests
Requires-Dist: typer[all]
License-File: LICENSE
License-File: AUTHORS.rst
Summary: Logseq Doctor: heal your Markdown files
Keywords: knowledge-base,knowledge-graph,logseq,logseq-plugin,markdown
Author: W Augusto Andreoli <andreoli@sent.com>
Author-email: "W. Augusto Andreoli" <andreoliwa@gmail.com>
License: MIT
Requires-Python: >=3.9
Project-URL: Changelog, https://logseq-doctor.readthedocs.io/en/latest/changelog.html
Project-URL: Documentation, https://logseq-doctor.readthedocs.io/
Project-URL: Issue Tracker, https://github.com/andreoliwa/logseq-doctor/issues
Project-URL: Source Code, https://github.com/andreoliwa/logseq-doctor
